MANIFEST.in
README.md
setup.py
SwampDragon_auth.egg-info/PKG-INFO
SwampDragon_auth.egg-info/SOURCES.txt
SwampDragon_auth.egg-info/dependency_links.txt
SwampDragon_auth.egg-info/requires.txt
SwampDragon_auth.egg-info/top_level.txt
swampdragon_auth/__init__.py
swampdragon_auth/socketconnection.py