Metadata-Version: 1.1
Name: SwampDragon-auth
Version: 0.1.3
Summary: Access signed in django users in routers
Home-page: https://github.com/jonashagstedt/swampdragon-auth
Author: Jonas Hagstedt
Author-email: hagstedt@gmail.com
License: BSD
Keywords: SwampDragon,SwampDragon-auth,auth,authentication
Platform: UNKNOWN
Classifier: Development Status :: 4 - Beta
Classifier: License :: OSI Approved :: BSD License
Classifier: Programming Language :: Python :: 2.7
Classifier: Programming Language :: Python :: 3
Classifier: Programming Language :: Python :: 3.3
Classifier: Programming Language :: Python :: 3.4
